EDutils/__init__.py
EDutils/convert_pets.sh
EDutils/display.py
EDutils/gui.py
EDutils/gui_config.py
EDutils/pets.py
EDutils/pets_ref.sh
EDutils/rotate_exp.py
EDutils/utilities.py
EDutils/viewers.py
EDutils/data/viewer_df.pkl
EDutils/data/viewer_dict.pkl
EDutils/sandbox/convert.py
EDutils/sandbox/test.py
blochwave/__init__.py
blochwave/bloch.py
blochwave/bloch_pp.py
blochwave/util.py
multislice/ED_base.py
multislice/Makefile
multislice/__init__.py
multislice/config.py
multislice/convert_pets.sh
multislice/import.py
multislice/interaction_parameter.py
multislice/multi_2D.py
multislice/multi_3D.py
multislice/multislice.py
multislice/mupy_utils.py
multislice/pets.py
multislice/postprocess.py
multislice/pymultislice.py
multislice/rotating_crystal.py
multislice/data/splines.npy
multislice/examples/.adxv_beam_center
multislice/examples/Carbone_SC.py
multislice/examples/Li.py
multislice/examples/biotin_figs.py
multislice/examples/biotin_run.py
multislice/examples/epicza.py
multislice/examples/ireloh.py
multislice/examples/make_crystal.py
multislice/examples/npy2smv
multislice/examples/npy2smv.cpp
multislice/examples/paracetamol_run.py
multislice/examples/silicon_run.py
multislice/examples/test_base.py
multislice/examples/walltimes.py
multislice/examples/dat/C.txt
multislice/examples/dat/H.txt
multislice/examples/dat/O.txt
multislice/examples/dat/P.txt
multislice/examples/dat/S.txt
multislice/examples/dat/biotin_m1.npy
multislice/examples/dat/biotin_m1.smv
multislice/examples/dat/biotin_m1.smv.npy
multislice/examples/dat/test.mp4
multislice/examples/dat/test.npy
multislice/examples/dat/test.smv
multislice/examples/dat/test.xyz
multislice/temsim/atompot.cpp
multislice/temsim/autoslic.cpp
multislice/temsim/autoslic.hpp
multislice/temsim/autosliccmd.cpp
multislice/temsim/autostem.cpp
multislice/temsim/autostem.hpp
multislice/temsim/autostemcmd.cpp
multislice/temsim/cfpix.cpp
multislice/temsim/cfpix.hpp
multislice/temsim/floatTIFF.cpp
multislice/temsim/floatTIFF.hpp
tarikED-1.0.8.dist-info/METADATA
tarikED-1.0.8.dist-info/WHEEL
tarikED-1.0.8.dist-info/top_level.txt
tarikED-1.0.8.dist-info/RECORD
